BlaskAPIAgentManager/__init__.py
BlaskAPIAgentManager/agent.py
BlaskAPIAgentManager/api_executor.py
BlaskAPIAgentManager/blask_pipeline.py
BlaskAPIAgentManager/fetch_id.py
BlaskAPIAgentManager/parameter_generator.py
BlaskAPIAgentManager/planner.py
BlaskAPIAgentManager/processor.py
BlaskAPIAgentManager/prompts.py
BlaskAPIAgentManager/result_synthesizer.py
BlaskAPIAgentManager/utils.py
tests/__init__.py
tests/test_api_agents.py
tests/test_basic.py
blaskapiagentmanager-0.1.22.dist-info/METADATA
blaskapiagentmanager-0.1.22.dist-info/WHEEL
blaskapiagentmanager-0.1.22.dist-info/top_level.txt
blaskapiagentmanager-0.1.22.dist-info/RECORD
