Metadata-Version: 2.4
Name: BlaskAPIAgentManager
Version: 0.1.22
Summary: An agent for interacting with Blask API based on Swagger spec
Home-page: https://gitlab.private.blask.com/blask/ml-ai/blaskapiagentmanager/-/tree/v1.22
Author: Blask RnD Team
Author-email: Blask RnD Team <elijah@blask.com>
License: MIT
Classifier: Programming Language :: Python :: 3
Classifier: License :: OSI Approved :: MIT License
Classifier: Operating System :: OS Independent
Requires-Python: >=3.9
Requires-Dist: langchain
Requires-Dist: langchain-openai
Requires-Dist: langchain-core
Requires-Dist: requests
Requires-Dist: python-dotenv
Requires-Dist: pydantic
Requires-Dist: openai
Requires-Dist: clickhouse-connect
Requires-Dist: langsmith>=0.3.32
Provides-Extra: dev
Requires-Dist: pytest; extra == "dev"
Requires-Dist: pytest-cov; extra == "dev"
Requires-Dist: black; extra == "dev"
Requires-Dist: isort; extra == "dev"
Requires-Dist: mypy; extra == "dev"
Dynamic: author
Dynamic: home-page
Dynamic: requires-python
